span_panel_api/__init__.py
span_panel_api/client.py
span_panel_api/const.py
span_panel_api/exceptions.py
span_panel_api/generated_client/__init__.py
span_panel_api/generated_client/api/__init__.py
span_panel_api/generated_client/api/default/__init__.py
span_panel_api/generated_client/api/default/delete_client_api_v1_auth_clients_name_delete.py
span_panel_api/generated_client/api/default/deprecated_spaces_endpoint_stub_api_v1_spaces_get.py
span_panel_api/generated_client/api/default/deprecated_spaces_endpoint_stub_api_v1_spaces_spaces_id_get.py
span_panel_api/generated_client/api/default/deprecated_spaces_endpoint_stub_api_v1_spaces_spaces_id_post.py
span_panel_api/generated_client/api/default/generate_jwt_api_v1_auth_register_post.py
span_panel_api/generated_client/api/default/get_all_clients_api_v1_auth_clients_get.py
span_panel_api/generated_client/api/default/get_circuit_state_api_v_1_circuits_circuit_id_get.py
span_panel_api/generated_client/api/default/get_circuits_api_v1_circuits_get.py
span_panel_api/generated_client/api/default/get_client_api_v1_auth_clients_name_get.py
span_panel_api/generated_client/api/default/get_islanding_state_api_v1_islanding_state_get.py
span_panel_api/generated_client/api/default/get_main_relay_state_api_v1_panel_grid_get.py
span_panel_api/generated_client/api/default/get_panel_meter_api_v1_panel_meter_get.py
span_panel_api/generated_client/api/default/get_panel_power_api_v1_panel_power_get.py
span_panel_api/generated_client/api/default/get_panel_state_api_v1_panel_get.py
span_panel_api/generated_client/api/default/get_storage_nice_to_have_threshold_api_v1_storage_nice_to_have_thresh_get.py
span_panel_api/generated_client/api/default/get_storage_soe_api_v1_storage_soe_get.py
span_panel_api/generated_client/api/default/get_wifi_scan_api_v1_wifi_scan_get.py
span_panel_api/generated_client/api/default/run_panel_emergency_reconnect_api_v1_panel_emergency_reconnect_post.py
span_panel_api-1.1.14.dist-info/METADATA
span_panel_api-1.1.14.dist-info/WHEEL
span_panel_api-1.1.14.dist-info/entry_points.txt
span_panel_api-1.1.14.dist-info/licenses/LICENSE
span_panel_api-1.1.14.dist-info/RECORD
