Metadata-Version: 2.4
Name: span-panel-api
Version: 1.1.14
Summary: A client library for SPAN Panel API
License-File: LICENSE
Author: SpanPanel
Requires-Python: >=3.10,<4.0
Classifier: Programming Language :: Python :: 3
Classifier: Programming Language :: Python :: 3.10
Classifier: Programming Language :: Python :: 3.11
Classifier: Programming Language :: Python :: 3.12
Classifier: Programming Language :: Python :: 3.13
Classifier: Programming Language :: Python :: 3.14
Requires-Dist: attrs (>=22.2.0)
Requires-Dist: click (>=8.0.0)
Requires-Dist: httpx (>=0.28.1,<0.29.0)
Requires-Dist: numpy (>=1.21.0)
Requires-Dist: python-dateutil (>=2.8.0)
Requires-Dist: pyyaml (>=6.0.0)
Project-URL: Homepage, https://github.com/SpanPanel/span-panel-api
Project-URL: Issues, https://github.com/SpanPanel/span-panel-api/issues
